[{"keywords": "NAME:(Python) and (AI OR ML)", "count": 31, "requirements": [{"name": "python", "count": 17, "persent": 18.478260869565215}, {"name": "ml", "count": 10, "persent": 10.869565217391305}, {"name": "git", "count": 7, "persent": 7.608695652173914}, {"name": "dl", "count": 6, "persent": 6.521739130434782}, {"name": "bash", "count": 6, "persent": 6.521739130434782}, {"name": "docker", "count": 6, "persent": 6.521739130434782}, {"name": "flask", "count": 3, "persent": 3.260869565217391}, {"name": "c", "count": 3, "persent": 3.260869565217391}, {"name": "cv", "count": 3, "persent": 3.260869565217391}, {"name": "opencv", "count": 3, "persent": 3.260869565217391}, {"name": "pytorch", "count": 3, "persent": 3.260869565217391}, {"name": "postgresql", "count": 2, "persent": 2.1739130434782608}, {"name": "linux", "count": 2, "persent": 2.1739130434782608}, {"name": "django", "count": 2, "persent": 2.1739130434782608}, {"name": "sqlalchemy", "count": 2, "persent": 2.1739130434782608}, {"name": "sql", "count": 2, "persent": 2.1739130434782608}, {"name": "crossvalidation", "count": 1, "persent": 1.0869565217391304}, {"name": "data_leaks", "count": 1, "persent": 1.0869565217391304}, {"name": "trees", "count": 1, "persent": 1.0869565217391304}, {"name": "boostings", "count": 1, "persent": 1.0869565217391304}, {"name": "mysql", "count": 1, "persent": 1.0869565217391304}, {"name": "framework", "count": 1, "persent": 1.0869565217391304}, {"name": "lega", "count": 1, "persent": 1.0869565217391304}, {"name": "y", "count": 1, "persent": 1.0869565217391304}, {"name": "ds", "count": 1, "persent": 1.0869565217391304}, {"name": "backend", "count": 1, "persent": 1.0869565217391304}, {"name": "everypixel", "count": 1, "persent": 1.0869565217391304}, {"name": "x", "count": 1, "persent": 1.0869565217391304}, {"name": "duplicat", "count": 1, "persent": 1.0869565217391304}, {"name": "ai", "count": 1, "persent": 1.0869565217391304}, {"name": "tornado", "count": 1, "persent": 1.0869565217391304}]}, {"keywords": "NAME:(Python OR Java) AND COMPANY_NAME:(1 OR 2 OR YANDEX) AND (DJANGO OR SPRING)", "count": 54, "requirements": [{"name": "java", "count": 9, "persent": 8.653846153846153}, {"name": "django", "count": 8, "persent": 7.6923076923076925}, {"name": "spring_boot", "count": 7, "persent": 6.730769230769231}, {"name": "spring_framework", "count": 6, "persent": 5.769230769230769}, {"name": "spring", "count": 4, "persent": 3.8461538461538463}, {"name": "git", "count": 4, "persent": 3.8461538461538463}, {"name": "python", "count": 4, "persent": 3.8461538461538463}, {"name": "docker", "count": 3, "persent": 2.8846153846153846}, {"name": "sql", "count": 3, "persent": 2.8846153846153846}, {"name": "java_se", "count": 3, "persent": 2.8846153846153846}, {"name": "netty_framework", "count": 3, "persent": 2.8846153846153846}, {"name": "api", "count": 2, "persent": 1.9230769230769231}, {"name": "flask", "count": 2, "persent": 1.9230769230769231}, {"name": "fastapi", "count": 2, "persent": 1.9230769230769231}, {"name": "framework", "count": 2, "persent": 1.9230769230769231}, {"name": "maven", "count": 2, "persent": 1.9230769230769231}, {"name": "js", "count": 2, "persent": 1.9230769230769231}, {"name": "core", "count": 2, "persent": 1.9230769230769231}, {"name": "ioc", "count": 1, "persent": 0.9615384615384616}, {"name": "spring_mvc", "count": 1, "persent": 0.9615384615384616}, {"name": "spring_data_jpa", "count": 1, "persent": 0.9615384615384616}, {"name": "spring_security", "count": 1, "persent": 0.9615384615384616}, {"name": "rest", "count": 1, "persent": 0.9615384615384616}, {"name": "postgresql", "count": 1, "persent": 0.9615384615384616}, {"name": "devops", "count": 1, "persent": 0.9615384615384616}, {"name": "dockercompose", "count": 1, "persent": 0.9615384615384616}, {"name": "orm", "count": 1, "persent": 0.9615384615384616}, {"name": "mvc", "count": 1, "persent": 0.9615384615384616}, {"name": "frameworks", "count": 1, "persent": 0.9615384615384616}, {"name": "restfull", "count": 1, "persent": 0.9615384615384616}, {"name": "soap", "count": 1, "persent": 0.9615384615384616}, {"name": "compose", "count": 1, "persent": 0.9615384615384616}, {"name": "netbeans", "count": 1, "persent": 0.9615384615384616}, {"name": "intellij", "count": 1, "persent": 0.9615384615384616}, {"name": "idea", "count": 1, "persent": 0.9615384615384616}, {"name": "svn", "count": 1, "persent": 0.9615384615384616}, {"name": "ant", "count": 1, "persent": 0.9615384615384616}, {"name": "solid", "count": 1, "persent": 0.9615384615384616}, {"name": "dry", "count": 1, "persent": 0.9615384615384616}, {"name": "kiss", "count": 1, "persent": 0.9615384615384616}, {"name": "etc", "count": 1, "persent": 0.9615384615384616}, {"name": "hub", "count": 1, "persent": 0.9615384615384616}, {"name": "swt", "count": 1, "persent": 0.9615384615384616}, {"name": "javafx", "count": 1, "persent": 0.9615384615384616}, {"name": "collections", "count": 1, "persent": 0.9615384615384616}, {"name": "concurrency", "count": 1, "persent": 0.9615384615384616}, {"name": "boot", "count": 1, "persent": 0.9615384615384616}, {"name": "security", "count": 1, "persent": 0.9615384615384616}, {"name": "data", "count": 1, "persent": 0.9615384615384616}, {"name": "gnu", "count": 1, "persent": 0.9615384615384616}, {"name": "linux", "count": 1, "persent": 0.9615384615384616}, {"name": "html", "count": 1, "persent": 0.9615384615384616}, {"name": "css", "count": 1, "persent": 0.9615384615384616}, {"name": "gradle", "count": 1, "persent": 0.9615384615384616}]}]